py_everything/__init__.py
py_everything/_data.py
py_everything/automation.py
py_everything/bencrypt.py
py_everything/conversion.py
py_everything/dateUtils.py
py_everything/error.py
py_everything/fileIO.py
py_everything/gitIt.py
py_everything/htmlXml.py
py_everything/maths.py
py_everything/mensuration.py
py_everything/path.py
py_everything/rand.py
py_everything/regex.py
py_everything/search.py
py_everything/sencrypt.py
py_everything/setupPyGen.py
py_everything/units.py
py_everything/web.py
py_everything-2.3.0.dist-info/LICENSE
py_everything-2.3.0.dist-info/METADATA
py_everything-2.3.0.dist-info/WHEEL
py_everything-2.3.0.dist-info/entry_points.txt
py_everything-2.3.0.dist-info/top_level.txt
py_everything-2.3.0.dist-info/RECORD
