Metadata-Version: 2.1
Name: py-everything
Version: 2.3.0
Summary: A python module containing all the basic functions and classes for python but doesn't stop at that, goes beyond advanced. From simple addition to advanced file encryption.
Home-page: https://github.com/pybash1/py_everything
Author: PyBash
Maintainer: PyBash
License: MIT License
Download-URL: https://pypi.org/project/py-everything/#files
Platform: UNKNOWN
Classifier: License :: OSI Approved :: MIT License
Classifier: Operating System :: OS Independent
Classifier: Natural Language :: English
Classifier: Development Status :: 5 - Production/Stable
Classifier: Programming Language :: Python :: Implementation :: CPython
Classifier: Intended Audience :: Developers
Classifier: Intended Audience :: Education
Classifier: Programming Language :: Python :: 3
Classifier: Programming Language :: Python :: 3.6
Classifier: Programming Language :: Python :: 3.7
Classifier: Programming Language :: Python :: 3.8
Classifier: Programming Language :: Python :: 3.9
Classifier: Topic :: Communications :: Email
Classifier: Topic :: Multimedia :: Video
Classifier: Topic :: Scientific/Engineering :: Physics
Classifier: Topic :: Scientific/Engineering :: Mathematics
Classifier: Topic :: Security :: Cryptography
Classifier: Topic :: Utilities
Classifier: Topic :: System :: Installation/Setup
Classifier: Topic :: System :: Archiving :: Packaging
Classifier: Topic :: Software Development :: Code Generators
Requires-Python: >=3.6
Requires-Dist: requests
Requires-Dist: playsound
Requires-Dist: setuptools
Requires-Dist: wheel
Requires-Dist: pip
Requires-Dist: enrocrypt
Requires-Dist: py-expression-eval
